{
    "videos": [
        {
            "videoId": "SgYdhBCn1jA",
            "title": "Pärchen-Check: Reicht ein Klaps auf den Po? | taff",
            "created_at": "2013-10-10",
            "comments": "2075",
            "duration": "PT9M35S",
            "views": "2808937",
            "ratings": 17714,
            "rating": "89.9",
            "snippet": {
                "publishedAt": "2013-10-10T14:49:29.000Z",
                "channelId": "UCZX_5XCRE_dZ_4tNXOEYtog",
                "title": "Pärchen-Check: Reicht ein Klaps auf den Po? | taff",
                "description": "Endlich verstehen was der Partner meint http://amzn.to/1bhAOOK ✘ Was ist das Geheimnis von glücklichen Paaren http://amzn.to/1QOf7H2 ✘ Hier gibt es heiße ...",
                "thumbnails": {
                    "default": {
                        "url": "https://i.ytimg.com/vi/SgYdhBCn1jA/default.jpg"
                    },
                    "medium": {
                        "url": "https://i.ytimg.com/vi/SgYdhBCn1jA/mqdefault.jpg"
                    },
                    "high": {
                        "url": "https://i.ytimg.com/vi/SgYdhBCn1jA/hqdefault.jpg"
                    }
                },
                "channelTitle": "taffOffiziell",
                "liveBroadcastContent": "none"
            }
        },
        {
            "videoId": "aUYy2tmi4Wk",
            "title": "Lauras (20) Geschichte über ihre Magersucht | taff",
            "created_at": "2013-11-26",
            "comments": "753",
            "duration": "PT8M23S",
            "views": "2418684",
            "ratings": 6013,
            "rating": "76.7",
            "snippet": {
                "publishedAt": "2013-11-26T16:04:02.000Z",
                "channelId": "UCZX_5XCRE_dZ_4tNXOEYtog",
                "title": "Lauras (20) Geschichte über ihre Magersucht | taff",
                "description": "Von 68 auf 47 Kilo in nur einem halben Jahr: Laura erzählt die Geschichte ihrer Magersucht Erkrankung. Aus einer Diät-Wette unter Freundinnen wurde schnell ...",
                "thumbnails": {
                    "default": {
                        "url": "https://i.ytimg.com/vi/aUYy2tmi4Wk/default.jpg"
                    },
                    "medium": {
                        "url": "https://i.ytimg.com/vi/aUYy2tmi4Wk/mqdefault.jpg"
                    },
                    "high": {
                        "url": "https://i.ytimg.com/vi/aUYy2tmi4Wk/hqdefault.jpg"
                    }
                },
                "channelTitle": "taffOffiziell",
                "liveBroadcastContent": "none"
            }
        },
        {
            "videoId": "HYFRZ6D_bqo",
            "title": "Das Problem großer Busen | taff",
            "created_at": "2013-10-10",
            "comments": "1384",
            "duration": "PT5M49S",
            "views": "1999611",
            "ratings": 8748,
            "rating": "81.0",
            "snippet": {
                "publishedAt": "2013-10-10T14:51:25.000Z",
                "channelId": "UCZX_5XCRE_dZ_4tNXOEYtog",
                "title": "Das Problem großer Busen | taff",
                "description": "Meike aus Berlin hat Körbchengröße Doppel H. Sie leidet sehr darunter, weil sie überall auf der Straße angegafft wird und inzwischen starke Rückenschmerzen ...",
                "thumbnails": {
                    "default": {
                        "url": "https://i.ytimg.com/vi/HYFRZ6D_bqo/default.jpg"
                    },
                    "medium": {
                        "url": "https://i.ytimg.com/vi/HYFRZ6D_bqo/mqdefault.jpg"
                    },
                    "high": {
                        "url": "https://i.ytimg.com/vi/HYFRZ6D_bqo/hqdefault.jpg"
                    }
                },
                "channelTitle": "taffOffiziell",
                "liveBroadcastContent": "none"
            }
        },
        {
            "videoId": "e-6sD0fw0r0",
            "title": "Magersucht in der Schwangerschaft | taff",
            "created_at": "2013-09-27",
            "comments": "430",
            "duration": "PT2M53S",
            "views": "1830666",
            "ratings": 12074,
            "rating": "90.7",
            "snippet": {
                "publishedAt": "2013-09-27T13:49:17.000Z",
                "channelId": "UCZX_5XCRE_dZ_4tNXOEYtog",
                "title": "Magersucht in der Schwangerschaft | taff",
                "description": "Holly Griffith ist 1,72 Meter groß und wiegt gerade mal 51 Kilo. Und das Schlimmste: Sie ist dabei noch im 9. Monat schwanger. Je größer ihr Baby wird, desto ...",
                "thumbnails": {
                    "default": {
                        "url": "https://i.ytimg.com/vi/e-6sD0fw0r0/default.jpg"
                    },
                    "medium": {
                        "url": "https://i.ytimg.com/vi/e-6sD0fw0r0/mqdefault.jpg"
                    },
                    "high": {
                        "url": "https://i.ytimg.com/vi/e-6sD0fw0r0/hqdefault.jpg"
                    }
                },
                "channelTitle": "taffOffiziell",
                "liveBroadcastContent": "none"
            }
        },
        {
            "videoId": "_hc7fJS2GVM",
            "title": "Fremde küssen sich | taff",
            "created_at": "2014-04-02",
            "comments": "2666",
            "duration": "PT8M40S",
            "views": "1827474",
            "ratings": 18289,
            "rating": "40.5",
            "snippet": {
                "publishedAt": "2014-04-02T13:00:07.000Z",
                "channelId": "UCZX_5XCRE_dZ_4tNXOEYtog",
                "title": "Fremde küssen sich | taff",
                "description": "Eine Künstlerin hat wildfremde Menschen sich vor der Kamera küssen lassen - manchmal zurückhaltend, manchmal leidenschaftlich, manchmal schüchtern.",
                "thumbnails": {
                    "default": {
                        "url": "https://i.ytimg.com/vi/_hc7fJS2GVM/default.jpg"
                    },
                    "medium": {
                        "url": "https://i.ytimg.com/vi/_hc7fJS2GVM/mqdefault.jpg"
                    },
                    "high": {
                        "url": "https://i.ytimg.com/vi/_hc7fJS2GVM/hqdefault.jpg"
                    }
                },
                "channelTitle": "taffOffiziell",
                "liveBroadcastContent": "none"
            }
        },
        {
            "videoId": "hAbK9lBbq68",
            "title": "Ehrgeiziger Vater im Beautyqueen-Wahn | taff",
            "created_at": "2014-12-02",
            "comments": "632",
            "duration": "PT7M5S",
            "views": "1812200",
            "ratings": 8311,
            "rating": "71.4",
            "snippet": {
                "publishedAt": "2014-12-02T15:00:07.000Z",
                "channelId": "UCZX_5XCRE_dZ_4tNXOEYtog",
                "title": "Ehrgeiziger Vater im Beautyqueen-Wahn | taff",
                "description": "Ein Vater drillt seine Kinder gnadenlos zu Beauty-Contests. Doch während er glaubt, seine Töchter bekannter als die Kardashian-Familie machen zu können, ...",
                "thumbnails": {
                    "default": {
                        "url": "https://i.ytimg.com/vi/hAbK9lBbq68/default.jpg"
                    },
                    "medium": {
                        "url": "https://i.ytimg.com/vi/hAbK9lBbq68/mqdefault.jpg"
                    },
                    "high": {
                        "url": "https://i.ytimg.com/vi/hAbK9lBbq68/hqdefault.jpg"
                    }
                },
                "channelTitle": "taffOffiziell",
                "liveBroadcastContent": "none"
            }
        },
        {
            "videoId": "Dl_19vdNVRw",
            "title": "Die Frau mit den Riesen-Brüsten: Busenwunder Lacey Wildd | taff",
            "created_at": "2014-01-19",
            "comments": "750",
            "duration": "PT6M1S",
            "views": "1639715",
            "ratings": 10375,
            "rating": "82.4",
            "snippet": {
                "publishedAt": "2014-01-19T16:00:06.000Z",
                "channelId": "UCZX_5XCRE_dZ_4tNXOEYtog",
                "title": "Die Frau mit den Riesen-Brüsten: Busenwunder Lacey Wildd | taff",
                "description": "Lacey Wildd wünscht sich nichts sehnlicher, als Millionärin zu werden. Um ihr Ziel zu erreichen, ist ihr kein Preis zu hoch und dafür setzt sie sogar ihr Leben aufs ...",
                "thumbnails": {
                    "default": {
                        "url": "https://i.ytimg.com/vi/Dl_19vdNVRw/default.jpg"
                    },
                    "medium": {
                        "url": "https://i.ytimg.com/vi/Dl_19vdNVRw/mqdefault.jpg"
                    },
                    "high": {
                        "url": "https://i.ytimg.com/vi/Dl_19vdNVRw/hqdefault.jpg"
                    }
                },
                "channelTitle": "taffOffiziell",
                "liveBroadcastContent": "none"
            }
        },
        {
            "videoId": "Un-y_O1UHu4",
            "title": "Die größten echten Brüste der Welt, Norma Stitz | taff",
            "created_at": "2013-10-14",
            "comments": "1710",
            "duration": "PT5M27S",
            "views": "1526731",
            "ratings": 8415,
            "rating": "80.8",
            "snippet": {
                "publishedAt": "2013-10-14T17:12:50.000Z",
                "channelId": "UCZX_5XCRE_dZ_4tNXOEYtog",
                "title": "Die größten echten Brüste der Welt, Norma Stitz | taff",
                "description": "Brust-OPs liegen voll im Trend. Doch wir zeigen euch eine Frau, die das nicht nötig hat. Sie steht sogar im Guiness-Buch der Rekorde, denn sie hat von Natur ...",
                "thumbnails": {
                    "default": {
                        "url": "https://i.ytimg.com/vi/Un-y_O1UHu4/default.jpg"
                    },
                    "medium": {
                        "url": "https://i.ytimg.com/vi/Un-y_O1UHu4/mqdefault.jpg"
                    },
                    "high": {
                        "url": "https://i.ytimg.com/vi/Un-y_O1UHu4/hqdefault.jpg"
                    }
                },
                "channelTitle": "taffOffiziell",
                "liveBroadcastContent": "none"
            }
        },
        {
            "videoId": "g6sF7_ilDhU",
            "title": "Ist tägliches Duschen wirklich ungesund? | taff",
            "created_at": "2013-12-15",
            "comments": "194",
            "duration": "PT4M49S",
            "views": "1409673",
            "ratings": 3133,
            "rating": "66.7",
            "snippet": {
                "publishedAt": "2013-12-15T12:30:01.000Z",
                "channelId": "UCZX_5XCRE_dZ_4tNXOEYtog",
                "title": "Ist tägliches Duschen wirklich ungesund? | taff",
                "description": "Ist es tatsächlich ungesund, jeden Tag zu duschen? Ist es gefährlich, während eines Gewitters duschen zu gehen? Wir haben bei Experten nachgefragt und die ...",
                "thumbnails": {
                    "default": {
                        "url": "https://i.ytimg.com/vi/g6sF7_ilDhU/default.jpg"
                    },
                    "medium": {
                        "url": "https://i.ytimg.com/vi/g6sF7_ilDhU/mqdefault.jpg"
                    },
                    "high": {
                        "url": "https://i.ytimg.com/vi/g6sF7_ilDhU/hqdefault.jpg"
                    }
                },
                "channelTitle": "taffOffiziell",
                "liveBroadcastContent": "none"
            }
        },
        {
            "videoId": "wq22cRNXu_A",
            "title": "Sexterror auf Gran Canaria - auf frischer Tat ertappt! | taff",
            "created_at": "2013-09-27",
            "comments": "218",
            "duration": "PT6M12S",
            "views": "1389281",
            "ratings": 7590,
            "rating": "87.0",
            "snippet": {
                "publishedAt": "2013-09-27T13:46:28.000Z",
                "channelId": "UCZX_5XCRE_dZ_4tNXOEYtog",
                "title": "Sexterror auf Gran Canaria - auf frischer Tat ertappt! | taff",
                "description": "Auf der Urlaubsinsel werden Spanner immer dreister. In der Nähe eines Familienstrands kommt es zur sexuellen Belästigung. Taff-Reporterin Kira Alin stellt die ...",
                "thumbnails": {
                    "default": {
                        "url": "https://i.ytimg.com/vi/wq22cRNXu_A/default.jpg"
                    },
                    "medium": {
                        "url": "https://i.ytimg.com/vi/wq22cRNXu_A/mqdefault.jpg"
                    },
                    "high": {
                        "url": "https://i.ytimg.com/vi/wq22cRNXu_A/hqdefault.jpg"
                    }
                },
                "channelTitle": "taffOffiziell",
                "liveBroadcastContent": "none"
            }
        },
        {
            "videoId": "VNoFDws64xI",
            "title": "Pärchen-Check: Battle im Freibad | taff",
            "created_at": "2013-09-27",
            "comments": "280",
            "duration": "PT5M48S",
            "views": "1359751",
            "ratings": 3134,
            "rating": "69.1",
            "snippet": {
                "publishedAt": "2013-09-27T13:48:08.000Z",
                "channelId": "UCZX_5XCRE_dZ_4tNXOEYtog",
                "title": "Pärchen-Check: Battle im Freibad | taff",
                "description": "Ihr wollt wissen, was euer Schatz wirklich meint mit dem was er sagt. Dieses schlaue Buch hilft euch dabei http://amzn.to/1dwn4BD. Was macht Paare glücklich?",
                "thumbnails": {
                    "default": {
                        "url": "https://i.ytimg.com/vi/VNoFDws64xI/default.jpg"
                    },
                    "medium": {
                        "url": "https://i.ytimg.com/vi/VNoFDws64xI/mqdefault.jpg"
                    },
                    "high": {
                        "url": "https://i.ytimg.com/vi/VNoFDws64xI/hqdefault.jpg"
                    }
                },
                "channelTitle": "taffOffiziell",
                "liveBroadcastContent": "none"
            }
        },
        {
            "videoId": "vfchlbKZhRA",
            "title": "Ungeschützter Sex auf der Wiesn | Oktoberfest 2013 | taff",
            "created_at": "2013-10-01",
            "comments": "530",
            "duration": "PT15M",
            "views": "1345489",
            "ratings": 6553,
            "rating": "43.5",
            "snippet": {
                "publishedAt": "2013-10-01T11:24:01.000Z",
                "channelId": "UCZX_5XCRE_dZ_4tNXOEYtog",
                "title": "Ungeschützter Sex auf der Wiesn | Oktoberfest 2013 | taff",
                "description": "taff - Oktoberfest - das größte Volksfest der Welt ist wieder in vollem Gange. Im vergangenen Jahr haben sich über 200.000 Deutsche beim ungeschützten Sex ...",
                "thumbnails": {
                    "default": {
                        "url": "https://i.ytimg.com/vi/vfchlbKZhRA/default.jpg"
                    },
                    "medium": {
                        "url": "https://i.ytimg.com/vi/vfchlbKZhRA/mqdefault.jpg"
                    },
                    "high": {
                        "url": "https://i.ytimg.com/vi/vfchlbKZhRA/hqdefault.jpg"
                    }
                },
                "channelTitle": "taffOffiziell",
                "liveBroadcastContent": "none"
            }
        },
        {
            "videoId": "yU7EMRnOd2w",
            "title": "Hot 5: \"Männer denken nicht an Sex, wenn sie dich sehen\" #8 | taff",
            "created_at": "2014-02-07",
            "comments": "383",
            "duration": "PT5M23S",
            "views": "1267613",
            "ratings": 11883,
            "rating": "92.3",
            "snippet": {
                "publishedAt": "2014-02-07T17:00:06.000Z",
                "channelId": "UCZX_5XCRE_dZ_4tNXOEYtog",
                "title": "Hot 5: \"Männer denken nicht an Sex, wenn sie dich sehen\" #8 | taff",
                "description": "Wissen Frauen eigentlich, was Männer sexy finden? Und wie ist die Selbsteinschätzung von Frauen? Fünf knackige Mädels wollen es wissen: Wer sieht am ...",
                "thumbnails": {
                    "default": {
                        "url": "https://i.ytimg.com/vi/yU7EMRnOd2w/default.jpg"
                    },
                    "medium": {
                        "url": "https://i.ytimg.com/vi/yU7EMRnOd2w/mqdefault.jpg"
                    },
                    "high": {
                        "url": "https://i.ytimg.com/vi/yU7EMRnOd2w/hqdefault.jpg"
                    }
                },
                "channelTitle": "taffOffiziell",
                "liveBroadcastContent": "none"
            }
        },
        {
            "videoId": "P2e6xX74SZw",
            "title": "Die jüngste Tätowiererin der Welt | taff",
            "created_at": "2014-07-06",
            "comments": "1857",
            "duration": "PT6M59S",
            "views": "1263691",
            "ratings": 15576,
            "rating": "92.7",
            "snippet": {
                "publishedAt": "2014-07-06T14:00:05.000Z",
                "channelId": "UCZX_5XCRE_dZ_4tNXOEYtog",
                "title": "Die jüngste Tätowiererin der Welt | taff",
                "description": "taff - Während andere Kinder in ihrem Alter noch mit Filzstiften malen, bemalt die 6-jährige Alicia im Tattoo-Studio ihres Vaters nackte Haut.",
                "thumbnails": {
                    "default": {
                        "url": "https://i.ytimg.com/vi/P2e6xX74SZw/default.jpg"
                    },
                    "medium": {
                        "url": "https://i.ytimg.com/vi/P2e6xX74SZw/mqdefault.jpg"
                    },
                    "high": {
                        "url": "https://i.ytimg.com/vi/P2e6xX74SZw/hqdefault.jpg"
                    }
                },
                "channelTitle": "taffOffiziell",
                "liveBroadcastContent": "none"
            }
        },
        {
            "videoId": "OepyXq_eADw",
            "title": "Das Manga-Mädchen | taff | ProSieben",
            "created_at": "2015-02-07",
            "comments": "1111",
            "duration": "PT8M53S",
            "views": "1262941",
            "ratings": 24582,
            "rating": "94.3",
            "snippet": {
                "publishedAt": "2015-02-07T15:00:01.000Z",
                "channelId": "UCZX_5XCRE_dZ_4tNXOEYtog",
                "title": "Das Manga-Mädchen | taff | ProSieben",
                "description": "taff – Immer montags bis freitags 17 Uhr auf ProSieben! Puppe oder Mensch? Anastasiya ist wohl das berühmteste Manga-Mädchen der Welt. Doch wer steckt ...",
                "thumbnails": {
                    "default": {
                        "url": "https://i.ytimg.com/vi/OepyXq_eADw/default.jpg"
                    },
                    "medium": {
                        "url": "https://i.ytimg.com/vi/OepyXq_eADw/mqdefault.jpg"
                    },
                    "high": {
                        "url": "https://i.ytimg.com/vi/OepyXq_eADw/hqdefault.jpg"
                    }
                },
                "channelTitle": "taffOffiziell",
                "liveBroadcastContent": "none"
            }
        },
        {
            "videoId": "YKtruHd1SNM",
            "title": "Mit Bibis Beauty Palace auf der Beauty-Messe | taff",
            "created_at": "2014-11-04",
            "comments": "996",
            "duration": "PT3M41S",
            "views": "1168271",
            "ratings": 24732,
            "rating": "96.2",
            "snippet": {
                "publishedAt": "2014-11-04T16:55:50.000Z",
                "channelId": "UCZX_5XCRE_dZ_4tNXOEYtog",
                "title": "Mit Bibis Beauty Palace auf der Beauty-Messe | taff",
                "description": "YouTuberin Bibi von Bibis Beauty Palace hat sich auf der Münchner Beauty-Messe nach den gefragtesten Trends und Must Haves für die kalten Herbsttage ...",
                "thumbnails": {
                    "default": {
                        "url": "https://i.ytimg.com/vi/YKtruHd1SNM/default.jpg"
                    },
                    "medium": {
                        "url": "https://i.ytimg.com/vi/YKtruHd1SNM/mqdefault.jpg"
                    },
                    "high": {
                        "url": "https://i.ytimg.com/vi/YKtruHd1SNM/hqdefault.jpg"
                    }
                },
                "channelTitle": "taffOffiziell",
                "liveBroadcastContent": "none"
            }
        },
        {
            "videoId": "LTk_P0F69Wc",
            "title": "Bibis Beauty Palace: Youtube-Star Bianca im Interview | taff",
            "created_at": "2014-08-21",
            "comments": "1553",
            "duration": "PT8M59S",
            "views": "1165933",
            "ratings": 7569,
            "rating": "65.2",
            "snippet": {
                "publishedAt": "2014-08-21T14:00:09.000Z",
                "channelId": "UCZX_5XCRE_dZ_4tNXOEYtog",
                "title": "Bibis Beauty Palace: Youtube-Star Bianca im Interview | taff",
                "description": "Bianca alias \"Bibi\" ist Deutschlands erfolgreichste Youtube-Bloggerin. Mit \"Bibis Beauty Palace\" startete sie online durch. Wie sie das geschafft hat, erzählt sie ...",
                "thumbnails": {
                    "default": {
                        "url": "https://i.ytimg.com/vi/LTk_P0F69Wc/default.jpg"
                    },
                    "medium": {
                        "url": "https://i.ytimg.com/vi/LTk_P0F69Wc/mqdefault.jpg"
                    },
                    "high": {
                        "url": "https://i.ytimg.com/vi/LTk_P0F69Wc/hqdefault.jpg"
                    }
                },
                "channelTitle": "taffOffiziell",
                "liveBroadcastContent": "none"
            }
        },
        {
            "videoId": "gM6gbdyOgik",
            "title": "Mein Beruf: Millionärsgattin | taff",
            "created_at": "2014-04-23",
            "comments": "843",
            "duration": "PT18M8S",
            "views": "1163845",
            "ratings": 7636,
            "rating": "12.8",
            "snippet": {
                "publishedAt": "2014-04-23T13:00:07.000Z",
                "channelId": "UCZX_5XCRE_dZ_4tNXOEYtog",
                "title": "Mein Beruf: Millionärsgattin | taff",
                "description": "Millionärsfrau Svetlana lebt dank des Vermögens ihres Mannes in Saus und Braus. Exklusiv gewährt sie uns einen Blick in ihr luxuriöses Leben.",
                "thumbnails": {
                    "default": {
                        "url": "https://i.ytimg.com/vi/gM6gbdyOgik/default.jpg"
                    },
                    "medium": {
                        "url": "https://i.ytimg.com/vi/gM6gbdyOgik/mqdefault.jpg"
                    },
                    "high": {
                        "url": "https://i.ytimg.com/vi/gM6gbdyOgik/hqdefault.jpg"
                    }
                },
                "channelTitle": "taffOffiziell",
                "liveBroadcastContent": "none"
            }
        },
        {
            "videoId": "a3D9pysQ52k",
            "title": "Hot 5: \"Spalt zwischen den Beinen ist sexy\" #13 | taff",
            "created_at": "2014-02-23",
            "comments": "971",
            "duration": "PT13M6S",
            "views": "1115992",
            "ratings": 8972,
            "rating": "32.6",
            "snippet": {
                "publishedAt": "2014-02-23T17:00:05.000Z",
                "channelId": "UCZX_5XCRE_dZ_4tNXOEYtog",
                "title": "Hot 5: \"Spalt zwischen den Beinen ist sexy\" #13 | taff",
                "description": "Wissen Frauen eigentlich, was Männer sexy finden? Und wie ist die Selbsteinschätzung von Frauen? Fünf knackige Mädels wollen es wissen: Wer sieht am ...",
                "thumbnails": {
                    "default": {
                        "url": "https://i.ytimg.com/vi/a3D9pysQ52k/default.jpg"
                    },
                    "medium": {
                        "url": "https://i.ytimg.com/vi/a3D9pysQ52k/mqdefault.jpg"
                    },
                    "high": {
                        "url": "https://i.ytimg.com/vi/a3D9pysQ52k/hqdefault.jpg"
                    }
                },
                "channelTitle": "taffOffiziell",
                "liveBroadcastContent": "none"
            }
        },
        {
            "videoId": "WlBncoEE81I",
            "title": "Hot 5: \"Bei meinen Brüsten sabbern die Männer\" #3 | taff",
            "created_at": "2014-01-29",
            "comments": "435",
            "duration": "PT5M1S",
            "views": "1112252",
            "ratings": 4509,
            "rating": "61.6",
            "snippet": {
                "publishedAt": "2014-01-29T13:39:02.000Z",
                "channelId": "UCZX_5XCRE_dZ_4tNXOEYtog",
                "title": "Hot 5: \"Bei meinen Brüsten sabbern die Männer\" #3 | taff",
                "description": "Wissen Frauen eigentlich, was Männer sexy finden? Und wie ist die Selbsteinschätzung von Frauen? Fünf knackige Mädels wollen es wissen: Wer sieht am ...",
                "thumbnails": {
                    "default": {
                        "url": "https://i.ytimg.com/vi/WlBncoEE81I/default.jpg"
                    },
                    "medium": {
                        "url": "https://i.ytimg.com/vi/WlBncoEE81I/mqdefault.jpg"
                    },
                    "high": {
                        "url": "https://i.ytimg.com/vi/WlBncoEE81I/hqdefault.jpg"
                    }
                },
                "channelTitle": "taffOffiziell",
                "liveBroadcastContent": "none"
            }
        },
        {
            "videoId": "P2c14i6P5Gk",
            "title": "\"Pack' deine Brüste aus\" - Das Brüste-JoJo einer dreisten Engländerin | taff",
            "created_at": "2014-01-25",
            "comments": "364",
            "duration": "PT7M12S",
            "views": "1055309",
            "ratings": 10228,
            "rating": "91.3",
            "snippet": {
                "publishedAt": "2014-01-25T17:00:04.000Z",
                "channelId": "UCZX_5XCRE_dZ_4tNXOEYtog",
                "title": "\"Pack' deine Brüste aus\" - Das Brüste-JoJo einer dreisten Engländerin  | taff",
                "description": "Zu klein? Zu groß? Wenn's um ihre Oberweite geht, kann sich die Engländerin Josie Cunningham einfach nicht entscheiden. Damit zieht sie allerdings auch den ...",
                "thumbnails": {
                    "default": {
                        "url": "https://i.ytimg.com/vi/P2c14i6P5Gk/default.jpg"
                    },
                    "medium": {
                        "url": "https://i.ytimg.com/vi/P2c14i6P5Gk/mqdefault.jpg"
                    },
                    "high": {
                        "url": "https://i.ytimg.com/vi/P2c14i6P5Gk/hqdefault.jpg"
                    }
                },
                "channelTitle": "taffOffiziell",
                "liveBroadcastContent": "none"
            }
        },
        {
            "videoId": "H_bFmesaSRw",
            "title": "Der größte Wasserrutschenpark Europas | taff",
            "created_at": "2013-10-29",
            "comments": "1129",
            "duration": "PT6M",
            "views": "1031749",
            "ratings": 7991,
            "rating": "51.9",
            "snippet": {
                "publishedAt": "2013-10-29T18:02:56.000Z",
                "channelId": "UCZX_5XCRE_dZ_4tNXOEYtog",
                "title": "Der größte Wasserrutschenpark Europas | taff",
                "description": "Der größte Wasserrutschenpark Europas ist der Siam Park. taff macht den Test: welche Rutsche ist am extremsten?",
                "thumbnails": {
                    "default": {
                        "url": "https://i.ytimg.com/vi/H_bFmesaSRw/default.jpg"
                    },
                    "medium": {
                        "url": "https://i.ytimg.com/vi/H_bFmesaSRw/mqdefault.jpg"
                    },
                    "high": {
                        "url": "https://i.ytimg.com/vi/H_bFmesaSRw/hqdefault.jpg"
                    }
                },
                "channelTitle": "taffOffiziell",
                "liveBroadcastContent": "none"
            }
        },
        {
            "videoId": "x1ivyKGJaG8",
            "title": "Mini-Miss: Wahl zur kleinen Schönheitskönigin | taff",
            "created_at": "2014-06-09",
            "comments": "2124",
            "duration": "PT5M56S",
            "views": "966390",
            "ratings": 7407,
            "rating": "79.6",
            "snippet": {
                "publishedAt": "2014-06-09T14:00:06.000Z",
                "channelId": "UCZX_5XCRE_dZ_4tNXOEYtog",
                "title": "Mini-Miss: Wahl zur kleinen Schönheitskönigin | taff",
                "description": "Viele Mütter wollen ihre Kleinen ganz früh groß raus bringen und schicken ihre Mädchen zu Schönheitswettbewerben. Ob so eine schöne Kindheit aussieht?",
                "thumbnails": {
                    "default": {
                        "url": "https://i.ytimg.com/vi/x1ivyKGJaG8/default.jpg"
                    },
                    "medium": {
                        "url": "https://i.ytimg.com/vi/x1ivyKGJaG8/mqdefault.jpg"
                    },
                    "high": {
                        "url": "https://i.ytimg.com/vi/x1ivyKGJaG8/hqdefault.jpg"
                    }
                },
                "channelTitle": "taffOffiziell",
                "liveBroadcastContent": "none"
            }
        },
        {
            "videoId": "5ZITC7J2E7k",
            "title": "Schottlands übergewichtigster Teenager: 200 Kilo mit 17 Jahren | taff",
            "created_at": "2014-10-23",
            "comments": "772",
            "duration": "PT9M4S",
            "views": "953694",
            "ratings": 8847,
            "rating": "93.6",
            "snippet": {
                "publishedAt": "2014-10-23T14:00:08.000Z",
                "channelId": "UCZX_5XCRE_dZ_4tNXOEYtog",
                "title": "Schottlands übergewichtigster Teenager: 200 Kilo mit 17 Jahren | taff",
                "description": "Die 17-jährige Amy wiegt fast 200 Kilo und ist bereits ein Pflegefall. Die Geschichte dahinter und die unfassbare Ausrede der Mutter seht ihr hier.",
                "thumbnails": {
                    "default": {
                        "url": "https://i.ytimg.com/vi/5ZITC7J2E7k/default.jpg"
                    },
                    "medium": {
                        "url": "https://i.ytimg.com/vi/5ZITC7J2E7k/mqdefault.jpg"
                    },
                    "high": {
                        "url": "https://i.ytimg.com/vi/5ZITC7J2E7k/hqdefault.jpg"
                    }
                },
                "channelTitle": "taffOffiziell",
                "liveBroadcastContent": "none"
            }
        },
        {
            "videoId": "6ZUSrtU-QDo",
            "title": "Plötzlich reich - Das Fake-Lotto-Experiment | taff",
            "created_at": "2014-11-06",
            "comments": "123",
            "duration": "PT5M14S",
            "views": "921407",
            "ratings": 1677,
            "rating": "68.8",
            "snippet": {
                "publishedAt": "2014-11-06T15:00:13.000Z",
                "channelId": "UCZX_5XCRE_dZ_4tNXOEYtog",
                "title": "Plötzlich reich - Das Fake-Lotto-Experiment | taff",
                "description": "Wie würden deine Freunde reagieren, wenn du plötzlich mehrere Hunderttausend Euro im Lotto gewinnen würdest? Die junge Jaquelina wollte genau das ...",
                "thumbnails": {
                    "default": {
                        "url": "https://i.ytimg.com/vi/6ZUSrtU-QDo/default.jpg"
                    },
                    "medium": {
                        "url": "https://i.ytimg.com/vi/6ZUSrtU-QDo/mqdefault.jpg"
                    },
                    "high": {
                        "url": "https://i.ytimg.com/vi/6ZUSrtU-QDo/hqdefault.jpg"
                    }
                },
                "channelTitle": "taffOffiziell",
                "liveBroadcastContent": "none"
            }
        },
        {
            "videoId": "bOmTvpMPieQ",
            "title": "Skurrile Dessous: C-Strings vs. invisible Strings | taff",
            "created_at": "2014-01-06",
            "comments": "268",
            "duration": "PT4M49S",
            "views": "913923",
            "ratings": 5811,
            "rating": "89.3",
            "snippet": {
                "publishedAt": "2014-01-06T15:15:50.000Z",
                "channelId": "UCZX_5XCRE_dZ_4tNXOEYtog",
                "title": "Skurrile Dessous: C-Strings vs. invisible Strings | taff",
                "description": "Ein Hauch von nichts - So kann man die neuen Slips bezeichnen Ob invisible String oder C-String - Wie alltagstauglich die Mini-Slips sind, soll ein ...",
                "thumbnails": {
                    "default": {
                        "url": "https://i.ytimg.com/vi/bOmTvpMPieQ/default.jpg"
                    },
                    "medium": {
                        "url": "https://i.ytimg.com/vi/bOmTvpMPieQ/mqdefault.jpg"
                    },
                    "high": {
                        "url": "https://i.ytimg.com/vi/bOmTvpMPieQ/hqdefault.jpg"
                    }
                },
                "channelTitle": "taffOffiziell",
                "liveBroadcastContent": "none"
            }
        },
        {
            "videoId": "DNOxx1miA7w",
            "title": "Beauty-Zwillinge durch viele Schönheitsoperationen | taff",
            "created_at": "2014-07-26",
            "comments": "132",
            "duration": "PT11M4S",
            "views": "847717",
            "ratings": 2705,
            "rating": "87.8",
            "snippet": {
                "publishedAt": "2014-07-26T14:00:10.000Z",
                "channelId": "UCZX_5XCRE_dZ_4tNXOEYtog",
                "title": "Beauty-Zwillinge durch viele Schönheitsoperationen | taff",
                "description": "Als Zwillinge sehen sich Joe und Kerry sowieso schon ähnlich, doch das reich ihnen nicht. 100.000 Euro haben die beiden schon für Operationen ausgegeben, ...",
                "thumbnails": {
                    "default": {
                        "url": "https://i.ytimg.com/vi/DNOxx1miA7w/default.jpg"
                    },
                    "medium": {
                        "url": "https://i.ytimg.com/vi/DNOxx1miA7w/mqdefault.jpg"
                    },
                    "high": {
                        "url": "https://i.ytimg.com/vi/DNOxx1miA7w/hqdefault.jpg"
                    }
                },
                "channelTitle": "taffOffiziell",
                "liveBroadcastContent": "none"
            }
        },
        {
            "videoId": "Dl4D1gpLtXU",
            "title": "taff Wasserrutschen-WM Reloaded #2 in München | taff",
            "created_at": "2013-10-29",
            "comments": "331",
            "duration": "PT5M23S",
            "views": "831280",
            "ratings": 10342,
            "rating": "94.0",
            "snippet": {
                "publishedAt": "2013-10-29T17:51:38.000Z",
                "channelId": "UCZX_5XCRE_dZ_4tNXOEYtog",
                "title": "taff Wasserrutschen-WM Reloaded #2 in München | taff",
                "description": "Vier sexy Promi-Damen messen sich auf den Rutschen verschiedener Aqua-Parks. *************************************** ▻ Ganze Folgen: http://bit.ly/p7taff ...",
                "thumbnails": {
                    "default": {
                        "url": "https://i.ytimg.com/vi/Dl4D1gpLtXU/default.jpg"
                    },
                    "medium": {
                        "url": "https://i.ytimg.com/vi/Dl4D1gpLtXU/mqdefault.jpg"
                    },
                    "high": {
                        "url": "https://i.ytimg.com/vi/Dl4D1gpLtXU/hqdefault.jpg"
                    }
                },
                "channelTitle": "taffOffiziell",
                "liveBroadcastContent": "none"
            }
        },
        {
            "videoId": "Yb3W4dYztXI",
            "title": "Die Frau, die niemals lacht | taff | ProSieben",
            "created_at": "2015-03-23",
            "comments": "326",
            "duration": "PT3M2S",
            "views": "828774",
            "ratings": 1547,
            "rating": "81.7",
            "snippet": {
                "publishedAt": "2015-03-23T15:00:01.000Z",
                "channelId": "UCZX_5XCRE_dZ_4tNXOEYtog",
                "title": "Die Frau, die niemals lacht | taff | ProSieben",
                "description": "Falten einfach wegbügeln http://amzn.to/1EUqydn ✘ Damit Du keine Falten bekommst http://amzn.to/1JbtGPJ ✘ Damit ihr immer was zu lachen habt ...",
                "thumbnails": {
                    "default": {
                        "url": "https://i.ytimg.com/vi/Yb3W4dYztXI/default.jpg"
                    },
                    "medium": {
                        "url": "https://i.ytimg.com/vi/Yb3W4dYztXI/mqdefault.jpg"
                    },
                    "high": {
                        "url": "https://i.ytimg.com/vi/Yb3W4dYztXI/hqdefault.jpg"
                    }
                },
                "channelTitle": "taffOffiziell",
                "liveBroadcastContent": "none"
            }
        },
        {
            "videoId": "3FIg4AwL9EY",
            "title": "Bikini-Test: Wer kann was tragen? | taff",
            "created_at": "2013-09-27",
            "comments": "176",
            "duration": "PT7M14S",
            "views": "794364",
            "ratings": 7633,
            "rating": "93.9",
            "snippet": {
                "publishedAt": "2013-09-27T13:59:20.000Z",
                "channelId": "UCZX_5XCRE_dZ_4tNXOEYtog",
                "title": "Bikini-Test: Wer kann was tragen? | taff",
                "description": "Was trägt Frau im Sommer am besten, wenn sie die eine oder andere Problemzone zu verstecken hat? Welcher Bikini passt zu welcher Figur und auf was sollte ...",
                "thumbnails": {
                    "default": {
                        "url": "https://i.ytimg.com/vi/3FIg4AwL9EY/default.jpg"
                    },
                    "medium": {
                        "url": "https://i.ytimg.com/vi/3FIg4AwL9EY/mqdefault.jpg"
                    },
                    "high": {
                        "url": "https://i.ytimg.com/vi/3FIg4AwL9EY/hqdefault.jpg"
                    }
                },
                "channelTitle": "taffOffiziell",
                "liveBroadcastContent": "none"
            }
        },
        {
            "videoId": "wBHw7DfMaWI",
            "title": "24 Stunden Tattoo-Marathon | taff | ProSieben",
            "created_at": "2015-01-14",
            "comments": "652",
            "duration": "PT19M16S",
            "views": "793731",
            "ratings": 4765,
            "rating": "71.5",
            "snippet": {
                "publishedAt": "2015-01-14T15:00:03.000Z",
                "channelId": "UCZX_5XCRE_dZ_4tNXOEYtog",
                "title": "24 Stunden Tattoo-Marathon | taff | ProSieben",
                "description": "Ein Tattoo für 20 Euro - Bei diesem Angebot stürmten hunderte Kunden ein Studio. Mehrere Stunden lang tätowierten der Chef und seine Angestellten für einen ...",
                "thumbnails": {
                    "default": {
                        "url": "https://i.ytimg.com/vi/wBHw7DfMaWI/default.jpg"
                    },
                    "medium": {
                        "url": "https://i.ytimg.com/vi/wBHw7DfMaWI/mqdefault.jpg"
                    },
                    "high": {
                        "url": "https://i.ytimg.com/vi/wBHw7DfMaWI/hqdefault.jpg"
                    }
                },
                "channelTitle": "taffOffiziell",
                "liveBroadcastContent": "none"
            }
        },
        {
            "videoId": "1ZVgqcrykbI",
            "title": "Hot 5: \"Bin zu geil für diese Welt\" #15 | taff",
            "created_at": "2014-03-02",
            "comments": "444",
            "duration": "PT9M20S",
            "views": "789750",
            "ratings": 3494,
            "rating": "74.2",
            "snippet": {
                "publishedAt": "2014-03-02T17:00:05.000Z",
                "channelId": "UCZX_5XCRE_dZ_4tNXOEYtog",
                "title": "Hot 5: \"Bin zu geil für diese Welt\"  #15 | taff",
                "description": "Wissen Frauen eigentlich, was Männer sexy finden? Und wie ist die Selbsteinschätzung von Frauen? Fünf knackige Mädels wollen es wissen: Wer sieht am ...",
                "thumbnails": {
                    "default": {
                        "url": "https://i.ytimg.com/vi/1ZVgqcrykbI/default.jpg"
                    },
                    "medium": {
                        "url": "https://i.ytimg.com/vi/1ZVgqcrykbI/mqdefault.jpg"
                    },
                    "high": {
                        "url": "https://i.ytimg.com/vi/1ZVgqcrykbI/hqdefault.jpg"
                    }
                },
                "channelTitle": "taffOffiziell",
                "liveBroadcastContent": "none"
            }
        },
        {
            "videoId": "ulJhwPervZA",
            "title": "Prostitution in Saarbrücken | taff",
            "created_at": "2014-04-13",
            "comments": "297",
            "duration": "PT9M37S",
            "views": "769358",
            "ratings": 5502,
            "rating": "94.4",
            "snippet": {
                "publishedAt": "2014-04-13T13:00:04.000Z",
                "channelId": "UCZX_5XCRE_dZ_4tNXOEYtog",
                "title": "Prostitution in Saarbrücken | taff",
                "description": "Saarbrücken hat ein großes Problem mit Prostitution. Nachdem in Frankreich Bordelle verboten wurden, fahren viele Franzosen über die Grenze, um sich ...",
                "thumbnails": {
                    "default": {
                        "url": "https://i.ytimg.com/vi/ulJhwPervZA/default.jpg"
                    },
                    "medium": {
                        "url": "https://i.ytimg.com/vi/ulJhwPervZA/mqdefault.jpg"
                    },
                    "high": {
                        "url": "https://i.ytimg.com/vi/ulJhwPervZA/hqdefault.jpg"
                    }
                },
                "channelTitle": "taffOffiziell",
                "liveBroadcastContent": "none"
            }
        },
        {
            "videoId": "WMt_axdMPoU",
            "title": "Weg mit den Tattoo-Jugendsünden | taff",
            "created_at": "2014-06-20",
            "comments": "713",
            "duration": "PT7M7S",
            "views": "768262",
            "ratings": 6835,
            "rating": "75.5",
            "snippet": {
                "publishedAt": "2014-06-20T14:00:06.000Z",
                "channelId": "UCZX_5XCRE_dZ_4tNXOEYtog",
                "title": "Weg mit den Tattoo-Jugendsünden | taff",
                "description": "taff - Manche Jugendsünden gehen richtig unter die Haut. Tattoomeisterin Ronja verwandelt gestochene Schluderarbeit in präzise Kunstwerke.",
                "thumbnails": {
                    "default": {
                        "url": "https://i.ytimg.com/vi/WMt_axdMPoU/default.jpg"
                    },
                    "medium": {
                        "url": "https://i.ytimg.com/vi/WMt_axdMPoU/mqdefault.jpg"
                    },
                    "high": {
                        "url": "https://i.ytimg.com/vi/WMt_axdMPoU/hqdefault.jpg"
                    }
                },
                "channelTitle": "taffOffiziell",
                "liveBroadcastContent": "none"
            }
        },
        {
            "videoId": "XPtCtzOI_aE",
            "title": "Totaler Barbie-Wahnsinn | taff | ProSieben",
            "created_at": "2014-12-21",
            "comments": "225",
            "duration": "PT4M50S",
            "views": "767492",
            "ratings": 4838,
            "rating": "93.9",
            "snippet": {
                "publishedAt": "2014-12-21T15:00:01.000Z",
                "channelId": "UCZX_5XCRE_dZ_4tNXOEYtog",
                "title": "Totaler Barbie-Wahnsinn | taff | ProSieben",
                "description": "Natürlichkeit ist ihr ein Graus! Blondie Bennett lässt nichts unversucht, um dem Schönheitsideal \"Barbie\" näher zu kommen. Dafür setzt sich die 38-Jährige ...",
                "thumbnails": {
                    "default": {
                        "url": "https://i.ytimg.com/vi/XPtCtzOI_aE/default.jpg"
                    },
                    "medium": {
                        "url": "https://i.ytimg.com/vi/XPtCtzOI_aE/mqdefault.jpg"
                    },
                    "high": {
                        "url": "https://i.ytimg.com/vi/XPtCtzOI_aE/hqdefault.jpg"
                    }
                },
                "channelTitle": "taffOffiziell",
                "liveBroadcastContent": "none"
            }
        },
        {
            "videoId": "UYCqjS0LRQY",
            "title": "Der neueste 3D Tattoo-Trend | taff",
            "created_at": "2014-07-30",
            "comments": "438",
            "duration": "PT1M37S",
            "views": "762179",
            "ratings": 7699,
            "rating": "99.1",
            "snippet": {
                "publishedAt": "2014-07-30T14:00:07.000Z",
                "channelId": "UCZX_5XCRE_dZ_4tNXOEYtog",
                "title": "Der neueste 3D Tattoo-Trend | taff",
                "description": "3D-Tattoos sind der neueste Trend und vor allem der absolute Hingucker. Jetzt bietet auch ein Deutscher diese Kunstwerke in seinem Studio in Berlin an.",
                "thumbnails": {
                    "default": {
                        "url": "https://i.ytimg.com/vi/UYCqjS0LRQY/default.jpg"
                    },
                    "medium": {
                        "url": "https://i.ytimg.com/vi/UYCqjS0LRQY/mqdefault.jpg"
                    },
                    "high": {
                        "url": "https://i.ytimg.com/vi/UYCqjS0LRQY/hqdefault.jpg"
                    }
                },
                "channelTitle": "taffOffiziell",
                "liveBroadcastContent": "none"
            }
        },
        {
            "videoId": "KqUSixz60n4",
            "title": "Tom Hiddleston Bonus Scenes Karaoke \"Stand by me\" in Berlin - Stars in Cars | taff",
            "created_at": "2013-11-14",
            "comments": "295",
            "duration": "PT15M10S",
            "views": "752060",
            "ratings": 3711,
            "rating": "66.8",
            "snippet": {
                "publishedAt": "2013-11-14T10:30:47.000Z",
                "channelId": "UCZX_5XCRE_dZ_4tNXOEYtog",
                "title": "Tom Hiddleston Bonus Scenes Karaoke \"Stand by me\" in Berlin - Stars in Cars | taff",
                "description": "Thor Star Tom Hiddleston (Loki) singt \"Stand by Me\" auf seiner Spritztour mit taff durch Berlin. Thor star Tom Hiddleston (Loki) is singing \"Stand by Me\" on his ...",
                "thumbnails": {
                    "default": {
                        "url": "https://i.ytimg.com/vi/KqUSixz60n4/default.jpg"
                    },
                    "medium": {
                        "url": "https://i.ytimg.com/vi/KqUSixz60n4/mqdefault.jpg"
                    },
                    "high": {
                        "url": "https://i.ytimg.com/vi/KqUSixz60n4/hqdefault.jpg"
                    }
                },
                "channelTitle": "taffOffiziell",
                "liveBroadcastContent": "none"
            }
        },
        {
            "videoId": "oted3DLYQR0",
            "title": "Hot 5: \"Du hast echt 'nen Gourmet-Hintern\" #9 | taff",
            "created_at": "2014-02-09",
            "comments": "561",
            "duration": "PT9M49S",
            "views": "742315",
            "ratings": 6889,
            "rating": "76.0",
            "snippet": {
                "publishedAt": "2014-02-09T17:00:06.000Z",
                "channelId": "UCZX_5XCRE_dZ_4tNXOEYtog",
                "title": "Hot 5: \"Du hast echt 'nen Gourmet-Hintern\" #9 | taff",
                "description": "Wissen Frauen eigentlich, was Männer sexy finden? Und wie ist die Selbsteinschätzung von Frauen? Fünf knackige Mädels wollen es wissen: Wer sieht am ...",
                "thumbnails": {
                    "default": {
                        "url": "https://i.ytimg.com/vi/oted3DLYQR0/default.jpg"
                    },
                    "medium": {
                        "url": "https://i.ytimg.com/vi/oted3DLYQR0/mqdefault.jpg"
                    },
                    "high": {
                        "url": "https://i.ytimg.com/vi/oted3DLYQR0/hqdefault.jpg"
                    }
                },
                "channelTitle": "taffOffiziell",
                "liveBroadcastContent": "none"
            }
        },
        {
            "videoId": "qkMGKbEP6MA",
            "title": "Das Hottest Girl Around: In Gleuel | taff | ProSieben",
            "created_at": "2015-01-21",
            "comments": "686",
            "duration": "PT7M2S",
            "views": "702489",
            "ratings": 2513,
            "rating": "53.7",
            "snippet": {
                "publishedAt": "2015-01-21T15:00:12.000Z",
                "channelId": "UCZX_5XCRE_dZ_4tNXOEYtog",
                "title": "Das Hottest Girl Around: In Gleuel | taff | ProSieben",
                "description": "Die Garantie für heiße Blicke – Hotpants http://amzn.to/1GyJucx ✘ Sexy Unterwäsche für gibt`s hier http://amzn.to/1EFt7xN ✘ Die passenden Klamotten für ...",
                "thumbnails": {
                    "default": {
                        "url": "https://i.ytimg.com/vi/qkMGKbEP6MA/default.jpg"
                    },
                    "medium": {
                        "url": "https://i.ytimg.com/vi/qkMGKbEP6MA/mqdefault.jpg"
                    },
                    "high": {
                        "url": "https://i.ytimg.com/vi/qkMGKbEP6MA/hqdefault.jpg"
                    }
                },
                "channelTitle": "taffOffiziell",
                "liveBroadcastContent": "none"
            }
        },
        {
            "videoId": "XzN29x0LW6E",
            "title": "Probleme für Studenten: Wohnung gegen Sex | taff",
            "created_at": "2013-11-07",
            "comments": "934",
            "duration": "PT5M",
            "views": "697194",
            "ratings": 4841,
            "rating": "76.9",
            "snippet": {
                "publishedAt": "2013-11-07T13:14:14.000Z",
                "channelId": "UCZX_5XCRE_dZ_4tNXOEYtog",
                "title": "Probleme für Studenten: Wohnung gegen Sex | taff",
                "description": "Der Wohnungsmarkt in deutschen Großstädten ist überlaufen. Da würden viele Leute wirklich alles für ein Dach über dem Kopf tun ... Wirklich alles?",
                "thumbnails": {
                    "default": {
                        "url": "https://i.ytimg.com/vi/XzN29x0LW6E/default.jpg"
                    },
                    "medium": {
                        "url": "https://i.ytimg.com/vi/XzN29x0LW6E/mqdefault.jpg"
                    },
                    "high": {
                        "url": "https://i.ytimg.com/vi/XzN29x0LW6E/hqdefault.jpg"
                    }
                },
                "channelTitle": "taffOffiziell",
                "liveBroadcastContent": "none"
            }
        },
        {
            "videoId": "a0w3y1hOIbo",
            "title": "Magersüchtige mit 29 Kilo | taff",
            "created_at": "2013-11-05",
            "comments": "732",
            "duration": "PT4M53S",
            "views": "681930",
            "ratings": 9634,
            "rating": "91.5",
            "snippet": {
                "publishedAt": "2013-11-05T13:44:51.000Z",
                "channelId": "UCZX_5XCRE_dZ_4tNXOEYtog",
                "title": "Magersüchtige mit 29 Kilo | taff",
                "description": "Ganze Folgen: http://bit.ly/p7taff ▻ taff bei Facebook: https://www.facebook.com/taff ▻ Folge uns bei twitter: https://twitter.com/taffnet ...",
                "thumbnails": {
                    "default": {
                        "url": "https://i.ytimg.com/vi/a0w3y1hOIbo/default.jpg"
                    },
                    "medium": {
                        "url": "https://i.ytimg.com/vi/a0w3y1hOIbo/mqdefault.jpg"
                    },
                    "high": {
                        "url": "https://i.ytimg.com/vi/a0w3y1hOIbo/hqdefault.jpg"
                    }
                },
                "channelTitle": "taffOffiziell",
                "liveBroadcastContent": "none"
            }
        },
        {
            "videoId": "wXlj1h_vr18",
            "title": "Luxusleben als Diebin | taff | ProSieben",
            "created_at": "2015-05-26",
            "comments": "210",
            "duration": "PT10M42S",
            "views": "675519",
            "ratings": 4752,
            "rating": "69.9",
            "snippet": {
                "publishedAt": "2015-05-26T14:00:06.000Z",
                "channelId": "UCZX_5XCRE_dZ_4tNXOEYtog",
                "title": "Luxusleben als Diebin | taff | ProSieben",
                "description": "taff – Immer montags bis freitags 17 Uhr auf ProSieben! Kim Farry ist Englands dreisterste Diebin. Die 54-jährige hat in den letzten Jahren Gegenstände im Wert ...",
                "thumbnails": {
                    "default": {
                        "url": "https://i.ytimg.com/vi/wXlj1h_vr18/default.jpg"
                    },
                    "medium": {
                        "url": "https://i.ytimg.com/vi/wXlj1h_vr18/mqdefault.jpg"
                    },
                    "high": {
                        "url": "https://i.ytimg.com/vi/wXlj1h_vr18/hqdefault.jpg"
                    }
                },
                "channelTitle": "taffOffiziell",
                "liveBroadcastContent": "none"
            }
        },
        {
            "videoId": "Yi_2HRAyGrM",
            "title": "Best of Hot 5 - Die peinlichsten Momente | taff",
            "created_at": "2014-06-21",
            "comments": "1192",
            "duration": "PT8M",
            "views": "675943",
            "ratings": 5276,
            "rating": "87.7",
            "snippet": {
                "publishedAt": "2014-06-21T14:00:05.000Z",
                "channelId": "UCZX_5XCRE_dZ_4tNXOEYtog",
                "title": "Best of Hot 5 - Die peinlichsten Momente | taff",
                "description": "Hier kommt eine geballte Ladung Hot 5! Viele leicht bekleidete Damen, eine Jury - das ist das Best of der Hot 5. *************************************** ▻Alle Hot 5 ...",
                "thumbnails": {
                    "default": {
                        "url": "https://i.ytimg.com/vi/Yi_2HRAyGrM/default.jpg"
                    },
                    "medium": {
                        "url": "https://i.ytimg.com/vi/Yi_2HRAyGrM/mqdefault.jpg"
                    },
                    "high": {
                        "url": "https://i.ytimg.com/vi/Yi_2HRAyGrM/hqdefault.jpg"
                    }
                },
                "channelTitle": "taffOffiziell",
                "liveBroadcastContent": "none"
            }
        },
        {
            "videoId": "R18V5NEpZZo",
            "title": "Bekannt aus \"Breaking Bad\": Teufelsdroge Crystal Meth | taff",
            "created_at": "2014-02-04",
            "comments": "638",
            "duration": "PT8M12S",
            "views": "672534",
            "ratings": 5392,
            "rating": "64.8",
            "snippet": {
                "publishedAt": "2014-02-04T17:00:07.000Z",
                "channelId": "UCZX_5XCRE_dZ_4tNXOEYtog",
                "title": "Bekannt aus \"Breaking Bad\": Teufelsdroge Crystal Meth | taff",
                "description": "Die Mode-Droge Crystal Meth - bekannt aus der Erfolgsserie Breaking Bad - gewinnt immer mehr an Popularität. Viele ahnen nicht, wie gefährlich sie eigentlich ...",
                "thumbnails": {
                    "default": {
                        "url": "https://i.ytimg.com/vi/R18V5NEpZZo/default.jpg"
                    },
                    "medium": {
                        "url": "https://i.ytimg.com/vi/R18V5NEpZZo/mqdefault.jpg"
                    },
                    "high": {
                        "url": "https://i.ytimg.com/vi/R18V5NEpZZo/hqdefault.jpg"
                    }
                },
                "channelTitle": "taffOffiziell",
                "liveBroadcastContent": "none"
            }
        }
    ]
}